odoo/addons/l10n_ch_mis_reports/README.rst
odoo/addons/l10n_ch_mis_reports/__init__.py
odoo/addons/l10n_ch_mis_reports/__manifest__.py
odoo/addons/l10n_ch_mis_reports/data/mis_report.xml
odoo/addons/l10n_ch_mis_reports/data/mis_report_kpi.xml
odoo/addons/l10n_ch_mis_reports/data/mis_report_style.xml
odoo/addons/l10n_ch_mis_reports/i18n/l10n_ch_mis_reports.pot
odoo/addons/l10n_ch_mis_reports/readme/CONFIGURE.rst
odoo/addons/l10n_ch_mis_reports/readme/CONTRIBUTORS.rst
odoo/addons/l10n_ch_mis_reports/readme/DESCRIPTION.rst
odoo/addons/l10n_ch_mis_reports/readme/INSTALL.rst
odoo/addons/l10n_ch_mis_reports/readme/ROADMAP.rst
odoo/addons/l10n_ch_mis_reports/readme/USAGE.rst
odoo/addons/l10n_ch_mis_reports/static/description/index.html
odoo11_addon_l10n_ch_mis_reports-11.0.1.1.0.dist-info/METADATA
odoo11_addon_l10n_ch_mis_reports-11.0.1.1.0.dist-info/RECORD
odoo11_addon_l10n_ch_mis_reports-11.0.1.1.0.dist-info/WHEEL
odoo11_addon_l10n_ch_mis_reports-11.0.1.1.0.dist-info/top_level.txt
